chrombigram/__init__.py
chrombigram/__main__.py
chrombigram/__version__.py
chrombigram/chrombigram.py
chrombigram/chrombigram_cumulative.py
chrombigram/precomputed.py
chrombigram/utilities.py
chrombigram-0.4.3.dist-info/LICENSE
chrombigram-0.4.3.dist-info/METADATA
chrombigram-0.4.3.dist-info/WHEEL
chrombigram-0.4.3.dist-info/top_level.txt
chrombigram-0.4.3.dist-info/RECORD
